horology/__init__.py
horology/fps.py
horology/tformatter.py
horology/timed_context.py
horology/timed_decorator.py
horology/timed_iterable.py
horology-1.4.1.dist-info/LICENSE
horology-1.4.1.dist-info/METADATA
horology-1.4.1.dist-info/WHEEL
horology-1.4.1.dist-info/RECORD
