Metadata-Version: 2.1
Name: horology
Version: 1.4.1
Summary: Conveniently measures the time of loops, contexts and functions.
Home-page: https://github.com/mjmikulski/horology
License: MIT
Keywords: timing,profiling,measure time,duration
Author: mjmikulski
Author-email: maciej.mikulski.jr@gmail.com
Requires-Python: >=3.10,<4.0
Classifier: Development Status :: 5 - Production/Stable
Classifier: Intended Audience :: Developers
Classifier: License :: OSI Approved :: MIT License
Classifier: Operating System :: OS Independent
Classifier: Programming Language :: Python :: 3
Classifier: Programming Language :: Python :: 3.10
Classifier: Programming Language :: Python :: 3.11
Classifier: Programming Language :: Python :: 3.12
Classifier: Programming Language :: Python :: 3.13
Classifier: Topic :: Software Development :: Libraries
Classifier: Topic :: Software Development :: Libraries :: Python Modules
Classifier: Topic :: Software Development :: Testing
Classifier: Topic :: Utilities
Project-URL: Repository, https://github.com/mjmikulski/horology
